strictprotocol/__init__.py
strictprotocol/core.py
strictprotocol/core.pyi
strictprotocol/py.typed
strictprotocol/safe_typing.py
strictprotocol-0.1.12.dist-info/licenses/LICENSE
strictprotocol-0.1.12.dist-info/METADATA
strictprotocol-0.1.12.dist-info/WHEEL
strictprotocol-0.1.12.dist-info/top_level.txt
strictprotocol-0.1.12.dist-info/RECORD
