Metadata-Version: 2.4
Name: strictprotocol
Version: 0.1.12
Summary: A stricter Protocol enforcement for Python
Author-email: Michael Afmokt <michael@esacca.com>
License-Expression: MIT
Project-URL: Homepage, https://github.com/afmkt/strictprotocol
Project-URL: Repository, https://github.com/afmkt/strictprotocol
Project-URL: Issues, https://github.com/afmkt/strictprotocol/issues
Keywords: protocol,typing,type-checking
Classifier: Programming Language :: Python :: 3
Classifier: Operating System :: OS Independent
Requires-Python: >=3.8
License-File: LICENSE
Dynamic: license-file
